runai_model_streamer/libstreamer/lib/libstreamers3.so
runai_model_streamer_s3/__init__.py
runai_model_streamer_s3/credentials/__init__.py
runai_model_streamer_s3/credentials/credentials.py
runai_model_streamer_s3/files/__init__.py
runai_model_streamer_s3/files/files.py
runai_model_streamer_s3/files/tests/__init__.py
runai_model_streamer_s3/files/tests/test_files.py
runai_model_streamer_s3-0.15.5.dist-info/LICENSE
runai_model_streamer_s3-0.15.5.dist-info/METADATA
runai_model_streamer_s3-0.15.5.dist-info/WHEEL
runai_model_streamer_s3-0.15.5.dist-info/top_level.txt
runai_model_streamer_s3-0.15.5.dist-info/RECORD
